equeue/__init__.py
equeue/rabbit/__init__.py
equeue/rabbit/publisher.py
equeue/rabbit/queue.py
equeue/rabbit/subscriber.py
equeue-0.1.4.dist-info/DESCRIPTION.rst
equeue-0.1.4.dist-info/METADATA
equeue-0.1.4.dist-info/RECORD
equeue-0.1.4.dist-info/WHEEL
equeue-0.1.4.dist-info/metadata.json
equeue-0.1.4.dist-info/top_level.txt
rabbit/__init__.py
rabbit/publisher.py
rabbit/queue.py
rabbit/subscriber.py
