Metadata-Version: 2.0
Name: equeue
Version: 0.1.4
Summary: Elastic Queue is a library to bear a PubSub projects. 
Home-page: https://github.com/jesuejunior/equeue
Author: Jesue Junior
Author-email: jesuesousa@gmail.com
License: UNKNOWN
Platform: UNKNOWN
Classifier: Intended Audience :: Developers
Classifier: License :: OSI Approved :: BSD License
Classifier: Programming Language :: Python
Classifier: Programming Language :: Python :: 2.7
Classifier: Programming Language :: Python :: 3
Classifier: Programming Language :: Python :: 3.5
Classifier: Programming Language :: Python :: Implementation :: PyPy
Classifier: Topic :: Software Development
Classifier: Topic :: Software Development :: Libraries
Classifier: Topic :: Software Development :: Libraries :: Python Modules
Requires-Dist: amqp (==2.1.0)
Requires-Dist: simplejson (>=3.8.2)
Requires-Dist: six (==1.10.0)
